bloqade/decoders/__init__.py
bloqade/decoders/_decoders/__init__.py
bloqade/decoders/_decoders/base.py
bloqade/decoders/_decoders/ldpc.py
bloqade/decoders/_decoders/mwpf.py
bloqade/decoders/_decoders/tesseract.py
bloqade/decoders/dialects/__init__.py
bloqade/decoders/dialects/annotate/__init__.py
bloqade/decoders/dialects/annotate/_dialect.py
bloqade/decoders/dialects/annotate/_interface.py
bloqade/decoders/dialects/annotate/stmts.py
bloqade/decoders/dialects/annotate/types.py
bloqade_decoders-0.3.0.dist-info/METADATA
bloqade_decoders-0.3.0.dist-info/WHEEL
bloqade_decoders-0.3.0.dist-info/licenses/LICENSE
bloqade_decoders-0.3.0.dist-info/RECORD
