Metadata-Version: 2.4
Name: bloqade-decoders
Version: 0.3.0
Summary: Decoder related statements and interfaces for Bloqade.
Author-email: johnzl-777 <jlong@quera.com>, rafaelha <rhaenel@quera.com>
License-File: LICENSE
Requires-Python: >=3.10
Requires-Dist: beliefmatching>=0.2.0
Requires-Dist: kirin-toolchain~=0.22.2
Requires-Dist: ldpc>=2.4.1
Requires-Dist: numpy>=2.2.6
Requires-Dist: stim>=1.15.0
Provides-Extra: mwpf
Requires-Dist: mwpf[stim]>=0.2.12; extra == 'mwpf'
Provides-Extra: tesseract
Requires-Dist: tesseract-decoder>=0.1.1.dev20260109233451; extra == 'tesseract'
